kma_url_api/__init__.py
kma_url_api/const.py
kma_url_api/nwp.py
kma_url_api/scripts.py
kma_url_api-2022.8.6.dist-info/METADATA
kma_url_api-2022.8.6.dist-info/WHEEL
kma_url_api-2022.8.6.dist-info/dependency_links.txt
kma_url_api-2022.8.6.dist-info/entry_points.txt
kma_url_api-2022.8.6.dist-info/top_level.txt
kma_url_api-2022.8.6.dist-info/RECORD
